{
  "main": {
    "id": "7ed11ac79e8a7b0c",
    "type": "split",
    "children": [
      {
        "id": "4934d630d1ce8d5e",
        "type": "tabs",
        "children": [
          {
            "id": "7b04d1d66e123142",
            "type": "leaf",
            "pinned": true,
            "state": {
              "type": "markdown",
              "state": {
                "file": "2 ACTIONS/_Focus.md",
                "mode": "source",
                "source": false
              },
              "pinned": true,
              "icon": "lucide-file",
              "title": "_Focus"
            }
          }
        ]
      }
    ],
    "direction": "vertical"
  },
  "left": {
    "id": "f913f5b97ac0092b",
    "type": "split",
    "children": [
      {
        "id": "0eec0109ef994595",
        "type": "tabs",
        "children": [
          {
            "id": "678e4aa493e2e01b",
            "type": "leaf",
            "state": {
              "type": "file-explorer",
              "state": {
                "sortOrder": "alphabetical",
                "autoReveal": false
              },
              "icon": "lucide-folder-closed",
              "title": "Files"
            }
          },
          {
            "id": "4ddade46eab2d121",
            "type": "leaf",
            "state": {
              "type": "search",
              "state": {
                "query": "",
                "matchingCase": false,
                "explainSearch": false,
                "collapseAll": false,
                "extraContext": false,
                "sortOrder": "alphabetical"
              },
              "icon": "lucide-search",
              "title": "Search"
            }
          },
          {
            "id": "3f509ebd8b47c090",
            "type": "leaf",
            "state": {
              "type": "bookmarks",
              "state": {},
              "icon": "lucide-bookmark",
              "title": "Bookmarks"
            }
          }
        ]
      }
    ],
    "direction": "horizontal",
    "width": 300,
    "collapsed": true
  },
  "right": {
    "id": "bb8c924bd69287fd",
    "type": "split",
    "children": [
      {
        "id": "15e32e9cda1b03e5",
        "type": "tabs",
        "children": [
          {
            "id": "15735fe7623e6f9e",
            "type": "leaf",
            "state": {
              "type": "backlink",
              "state": {
                "file": "2 ACTIONS/_Focus.md",
                "collapseAll": false,
                "extraContext": false,
                "sortOrder": "alphabetical",
                "showSearch": false,
                "searchQuery": "",
                "backlinkCollapsed": false,
                "unlinkedCollapsed": true
              },
              "icon": "links-coming-in",
              "title": "Backlinks for _Focus"
            }
          },
          {
            "id": "72dfc28a5b519510",
            "type": "leaf",
            "state": {
              "type": "outgoing-link",
              "state": {
                "file": "2 ACTIONS/_Focus.md",
                "linksCollapsed": false,
                "unlinkedCollapsed": true
              },
              "icon": "links-going-out",
              "title": "Outgoing links from _Focus"
            }
          },
          {
            "id": "c4666aebcd1f025d",
            "type": "leaf",
            "state": {
              "type": "tag",
              "state": {
                "sortOrder": "frequency",
                "useHierarchy": true,
                "showSearch": false,
                "searchQuery": ""
              },
              "icon": "lucide-tags",
              "title": "Tags"
            }
          },
          {
            "id": "95d7552a43ce04d4",
            "type": "leaf",
            "state": {
              "type": "all-properties",
              "state": {
                "sortOrder": "frequency",
                "showSearch": false,
                "searchQuery": ""
              },
              "icon": "lucide-archive",
              "title": "All properties"
            }
          },
          {
            "id": "f7134d209dd2185a",
            "type": "leaf",
            "state": {
              "type": "outline",
              "state": {
                "file": "2 ACTIONS/_Focus.md",
                "followCursor": false,
                "showSearch": false,
                "searchQuery": ""
              },
              "icon": "lucide-list",
              "title": "Outline of _Focus"
            }
          }
        ]
      }
    ],
    "direction": "horizontal",
    "width": 300,
    "collapsed": true
  },
  "left-ribbon": {
    "hiddenItems": {
      "switcher:Open quick switcher": false,
      "graph:Open graph view": false,
      "canvas:Create new canvas": false,
      "daily-notes:Open today's daily note": false,
      "templates:Insert template": false,
      "command-palette:Open command palette": false,
      "bases:Create new base": false,
      "homepage:Open homepage": false,
      "table-editor-obsidian:Advanced Tables Toolbar": false,
      "obsidian-kanban:Create new board": false,
      "pdf-plus:PDF++: Toggle auto-copy": false,
      "pdf-plus:PDF++: Toggle auto-focus": false,
      "pdf-plus:PDF++: Toggle auto-paste": false,
      "obsidian-excalidraw-plugin:New drawing": false
    }
  },
  "active": "7b04d1d66e123142",
  "lastOpenFiles": [
    "image/Pasted image 20260204121726.png",
    "image/Pasted image 20260203122439.png",
    "image/Pasted image 20260203122436.png",
    "image/Pasted image 20260203122245.png",
    "image/Pasted image 20260203121729.png",
    "image/Pasted image 20260203121532.png",
    "image/Pasted image 20260203120745.png",
    "image/Pasted image 20260203115943.png",
    "image/Pasted image 20260203115248.png",
    "image/Pasted image 20260202155058.png",
    "image/Pasted image 20260202155013.png",
    "Data.md",
    "Continuous Learning & Nested Learning Survey (main).md",
    "Continual Learning Code.md"
  ]
}